README.md
setup.cfg
setup.py
graphical_password/__init__.py
graphical_password/exceptions.py
graphical_password/graphical_password.py
graphical_password/image_examples.py
graphical_password/tree.py
graphical_password.egg-info/PKG-INFO
graphical_password.egg-info/SOURCES.txt
graphical_password.egg-info/dependency_links.txt
graphical_password.egg-info/not-zip-safe
graphical_password.egg-info/top_level.txt