Metadata-Version: 2.1
Name: graphical-password
Version: 2.0
Summary: Simple authorization creation based on a sequence of images
Author-email: egubareva06@mail.ru
